COPYRIGHT
MANIFEST.in
setup.py
dblatex.egg-info/PKG-INFO
dblatex.egg-info/SOURCES.txt
dblatex.egg-info/dependency_links.txt
dblatex.egg-info/top_level.txt
docs/Logo_Freexian.png
docs/Makefile
docs/biblio.xml
docs/covers.xml
docs/document.xml
docs/faq.xml
docs/figure.xml
docs/footnote.xml
docs/formatting.xml
docs/froglogic-logo.png
docs/index.xml
docs/install.xml
docs/introduction.xml
docs/locale.xml
docs/manual.conf
docs/manual.css
docs/manual.db
docs/manual.pdf
docs/manual.xml
docs/manual.xsl
docs/music.xml
docs/olinkdb.xml
docs/pagesetup.xml
docs/pagesetup2.fig
docs/pagesetup2.pdf
docs/processus.eps
docs/processus.fig
docs/publish.xml
docs/release-notes.db
docs/release-notes.pdf
docs/revision.xml
docs/secnum.xml
docs/thanks.xml
docs/verbatim.xml
docs/version.xml
docs/xref.xml
docs/changes/changes-0.1.10.xml
docs/changes/changes-0.1.4.1.xml
docs/changes/changes-0.1.4.xml
docs/changes/changes-0.1.5.xml
docs/changes/changes-0.1.6.xml
docs/changes/changes-0.1.7.xml
docs/changes/changes-0.1.8.xml
docs/changes/changes-0.1.9.xml
docs/changes/changes-0.2.1.xml
docs/changes/changes-0.2.10.xml
docs/changes/changes-0.2.11.xml
docs/changes/changes-0.2.12.xml
docs/changes/changes-0.2.2.xml
docs/changes/changes-0.2.3.xml
docs/changes/changes-0.2.4.xml
docs/changes/changes-0.2.5.xml
docs/changes/changes-0.2.6.xml
docs/changes/changes-0.2.7.xml
docs/changes/changes-0.2.8.xml
docs/changes/changes-0.2.9.xml
docs/changes/changes-0.2.xml
docs/changes/changes-0.2pre.xml
docs/changes/changes-0.3.1.xml
docs/changes/changes-0.3.10.xml
docs/changes/changes-0.3.2.xml
docs/changes/changes-0.3.3.xml
docs/changes/changes-0.3.4.xml
docs/changes/changes-0.3.5.xml
docs/changes/changes-0.3.6.xml
docs/changes/changes-0.3.7.xml
docs/changes/changes-0.3.8.xml
docs/changes/changes-0.3.9.xml
docs/changes/changes-0.3.xml
docs/changes/changes.txt
docs/changes/release-notes.xml
docs/custom/custom.xml
docs/custom/dblatex.xconf
docs/custom/mystyle.sty
docs/custom/param.xml
docs/custom/specparam.xml
docs/custom/stycommand.xml
docs/custom/stydebug.xml
docs/custom/style.xml
docs/custom/styoption.xml
docs/custom/stypackage.xml
