Metadata-Version: 1.1
Name: dblatex
Version: 0.3.10
Summary: DocBook to LaTeX/ConTeXt Publishing
Home-page: http://dblatex.sf.net
Author: Benoit Guillon
Author-email: marsgui@users.sourceforge.net
License: GPL Version 2 or later
Platform: UNKNOWN
Classifier: Operating System :: OS Independent
Classifier: Topic :: Text Processing :: Markup :: XML
Classifier: License :: OSI Approved :: GNU General Public License (GPL)
